flexi_prompt/README.md
flexi_prompt/__init__.py
flexi_prompt/flexi_prompt.py
flexi_prompt-0.1.0.dist-info/METADATA
flexi_prompt-0.1.0.dist-info/WHEEL
flexi_prompt-0.1.0.dist-info/RECORD
