Metadata-Version: 2.3
Name: flexi_prompt
Version: 0.1.0
Summary: A flexible prompt builder for AI applications
Project-URL: Homepage, https://github.com/VELIKII-DIVAN/FlexiPrompt
Project-URL: Repository, https://github.com/VELIKII-DIVAN/FlexiPrompt.git
Author-email: Dmitrii Minaev <dmitriy.minaev.v@gmail.com>
License-Expression: MIT
Requires-Python: >=3.8
